karrio/server/events/__init__.py
karrio/server/events/admin.py
karrio/server/events/apps.py
karrio/server/events/filters.py
karrio/server/events/models.py
karrio/server/events/router.py
karrio/server/events/signals.py
karrio/server/events/tasks.py
karrio/server/events/tests.py
karrio/server/events/urls.py
karrio/server/events/migrations/0001_initial.py
karrio/server/events/migrations/0002_event.py
karrio/server/events/migrations/0003_auto_20220303_1210.py
karrio/server/events/migrations/0004_custom_migration_2022_4.py
karrio/server/events/migrations/0005_event_event_object_idx.py
karrio/server/events/migrations/0006_webhook_events_alter_event_data.py
karrio/server/events/migrations/0007_auto_20221130_0255.py
karrio/server/events/migrations/0008_alter_event_type.py
karrio/server/events/migrations/0009_alter_webhook_enabled_events.py
karrio/server/events/migrations/0010_event_event_created_at_idx.py
karrio/server/events/migrations/__init__.py
karrio/server/events/serializers/__init__.py
karrio/server/events/serializers/base.py
karrio/server/events/serializers/event.py
karrio/server/events/serializers/webhook.py
karrio/server/events/task_definitions/__init__.py
karrio/server/events/task_definitions/base/__init__.py
karrio/server/events/task_definitions/base/archiving.py
karrio/server/events/task_definitions/base/tracking.py
karrio/server/events/task_definitions/base/webhook.py
karrio/server/events/tests/__init__.py
karrio/server/events/tests/test_events.py
karrio/server/events/tests/test_tracking_tasks.py
karrio/server/events/tests/test_webhooks.py
karrio/server/events/views/__init__.py
karrio/server/events/views/webhooks.py
karrio/server/graph/schemas/__init__.py
karrio/server/graph/schemas/events/__init__.py
karrio/server/graph/schemas/events/inputs.py
karrio/server/graph/schemas/events/mutations.py
karrio/server/graph/schemas/events/types.py
karrio_server_events-2026.1.4.dist-info/METADATA
karrio_server_events-2026.1.4.dist-info/WHEEL
karrio_server_events-2026.1.4.dist-info/top_level.txt
karrio_server_events-2026.1.4.dist-info/RECORD
